xmlschema/__init__.py
xmlschema/_limits.py
xmlschema/aliases.py
xmlschema/arguments.py
xmlschema/cli.py
xmlschema/dataobjects.py
xmlschema/documents.py
xmlschema/exceptions.py
xmlschema/exports.py
xmlschema/limits.py
xmlschema/loaders.py
xmlschema/locations.py
xmlschema/names.py
xmlschema/namespaces.py
xmlschema/py.typed
xmlschema/settings.py
xmlschema/translation.py
xmlschema/converters/__init__.py
xmlschema/converters/abdera.py
xmlschema/converters/badgerfish.py
xmlschema/converters/base.py
xmlschema/converters/columnar.py
xmlschema/converters/gdata.py
xmlschema/converters/jsonml.py
xmlschema/converters/parker.py
xmlschema/converters/unordered.py
xmlschema/extras/__init__.py
xmlschema/extras/codegen.py
xmlschema/extras/wsdl.py
xmlschema/extras/templates/python/bindings.py.jinja
xmlschema/extras/templates/python/sample.py.jinja
xmlschema/locale/en/LC_MESSAGES/xmlschema.mo
xmlschema/locale/en/LC_MESSAGES/xmlschema.po
xmlschema/locale/it/LC_MESSAGES/xmlschema.mo
xmlschema/locale/it/LC_MESSAGES/xmlschema.po
xmlschema/locale/pl/LC_MESSAGES/xmlschema.mo
xmlschema/locale/pl/LC_MESSAGES/xmlschema.po
xmlschema/locale/ru/LC_MESSAGES/xmlschema.mo
xmlschema/locale/ru/LC_MESSAGES/xmlschema.po
xmlschema/resources/__init__.py
xmlschema/resources/fetchers.py
xmlschema/resources/parsers.py
xmlschema/resources/sax.py
xmlschema/resources/xml_loader.py
xmlschema/resources/xml_resource.py
xmlschema/schemas/DSIG/xmldsig-core-schema.xsd
xmlschema/schemas/DSIG/xmldsig11-schema.xsd
xmlschema/schemas/HFP/XMLSchema-hasFacetAndProperty.xsd
xmlschema/schemas/VC/XMLSchema-versioning.xsd
xmlschema/schemas/WSDL/soap-encoding.xsd
xmlschema/schemas/WSDL/soap-envelope.xsd
xmlschema/schemas/WSDL/wsdl-soap.xsd
xmlschema/schemas/WSDL/wsdl.xsd
xmlschema/schemas/XENC/xenc-schema-11.xsd
xmlschema/schemas/XENC/xenc-schema.xsd
xmlschema/schemas/XHTML/xhtml1-strict.xsd
xmlschema/schemas/XLINK/xlink.xsd
xmlschema/schemas/XML/xml.xsd
xmlschema/schemas/XSD_1.0/XMLSchema.xsd
xmlschema-4.3.0.dist-info/licenses/LICENSE
xmlschema-4.3.0.dist-info/METADATA
xmlschema-4.3.0.dist-info/WHEEL
xmlschema-4.3.0.dist-info/entry_points.txt
xmlschema-4.3.0.dist-info/top_level.txt
xmlschema-4.3.0.dist-info/RECORD
